AtomicDecoders.py
atomicdecoders-1.6.2.dist-info/LICENSE
atomicdecoders-1.6.2.dist-info/METADATA
atomicdecoders-1.6.2.dist-info/WHEEL
atomicdecoders-1.6.2.dist-info/RECORD
